{
  "resourceType": "StructureDefinition",
  "id": "ProblemOrDiagnosis",
  "extension": [
    {
      "url": "https://aehrc.csiro.au/fhir/StructureDefinition/associated-image",
      "valueReference": {
        "reference": "Binary/IMG19077"
      }
    }
  ],
  "url": "https://aehrc.csiro.au/fhir/logical-models/ProblemOrDiagnosis",
  "name": "ProblemOrDiagnosis",
  "title": "Problem Or Diagnosis",
  "status": "draft",
  "publisher": "CSIRO",
  "description": "Details about a single identified health condition, injury, disability or any other issue which impacts on the physical, mental and/or social well-being of an individual.​",
  "fhirVersion": "4.0.1",
  "kind": "logical",
  "abstract": false,
  "type": "https://aehrc.csiro.au/fhir/logical-models/ProblemOrDiagnosis",
  "baseDefinition": "http://hl7.org/fhir/StructureDefinition/Base",
  "derivation": "specialization",
  "differential": {
    "element": [
      {
        "id": "ProblemOrDiagnosis",
        "path": "ProblemOrDiagnosis",
        "short": "Problem Or Diagnosis",
        "definition": "Details about a single identified health condition, injury, disability or any other issue which impacts on the physical, mental and/or social well-being of an individual.​",
        "alias": [
          "Condition",
          "History"
        ],
        "min": 0,
        "max": "*",
        "type": [
          {
            "code": "BackboneElement"
          }
        ]
      },
      {
        "id": "ProblemOrDiagnosis.ProblemOrDiagnosisName",
        "path": "ProblemOrDiagnosis.ProblemOrDiagnosisName",
        "short": "Problem Or Diagnosis Name",
        "definition": "Identification of the problem or diagnosis, by name.",
        "min": 1,
        "max": "1",
        "type": [
          {
            "code": "CodeableConcept"
          }
        ]
      },
      {
        "id": "ProblemOrDiagnosis.BodySite",
        "path": "ProblemOrDiagnosis.BodySite",
        "short": "Body Site",
        "definition": "Anatomical descriptor/concept",
        "min": 0,
        "max": "1",
        "type": [
          {
            "code": "CodeableConcept"
          }
        ]
      },
      {
        "path": "ProblemOrDiagnosis.Laterality",
        "short": "Laterality",
        "definition": "The side of the body where the problem or diagnosis is present,",
        "min": 0,
        "max": "1",
        "type": [
          {
            "code": "CodeableConcept"
          }
        ]
      },
      {
        "id": "ProblemOrDiagnosis.Status",
        "path": "ProblemOrDiagnosis.Status",
        "short": "Status",
        "definition": "A data element that records whether the condition is active or inactive.",
        "min": 0,
        "max": "1",
        "type": [
          {
            "code": "CodeableConcept"
          }
        ]
      },
      {
        "id": "ProblemOrDiagnosis.Comment",
        "path": "ProblemOrDiagnosis.Comment",
        "short": "Comment",
        "definition": "Additional narrative about the problem or diagnosis not captured in other fields.",
        "alias": [
          "Note",
          "Further details"
        ],
        "min": 0,
        "max": "1",
        "type": [
          {
            "code": "string"
          }
        ]
      }
    ]
  }
}